terminalplot/__init__.py
terminalplot/_version.py
terminalplot/command.py
terminalplot/terminalplot.py
terminalplot/test/__init__.py
terminalplot/test/test_terminalplot.py
terminalplot-0.4.0.dist-info/METADATA
terminalplot-0.4.0.dist-info/WHEEL
terminalplot-0.4.0.dist-info/entry_points.txt
terminalplot-0.4.0.dist-info/licenses/LICENCE.txt
terminalplot-0.4.0.dist-info/RECORD
