Metadata-Version: 2.1
Name: terminalplot
Version: 0.4.0
Summary: Plot points in terminal
Project-URL: Source, https://github.com/kressi/terminalplot
Author-email: Michael Kressibucher <michael.kressibucher@gmail.com>
License:                     GNU GENERAL PUBLIC LICENSE
License-File: LICENCE.txt
Keywords: console,graph,plot,terminal
Classifier: Environment :: Console
Classifier: Intended Audience :: Developers
Classifier: License :: OSI Approved :: GNU General Public License v3 or later (GPLv3+)
Classifier: Operating System :: POSIX
Classifier: Programming Language :: Python :: 3
Classifier: Topic :: Scientific/Engineering :: Visualization
Requires-Python: >3.3
Provides-Extra: dev
Requires-Dist: black; extra == 'dev'
Requires-Dist: mypy; extra == 'dev'
Requires-Dist: pytest; extra == 'dev'
Requires-Dist: pytest-cov; extra == 'dev'
Requires-Dist: ruff; extra == 'dev'
